LICENSE
MANIFEST.in
README.md
setup.py
bin/w3cpull
w3cpull/__init__.py
w3cpull/chromedriver_darwin
w3cpull/chromedriver_linux
w3cpull/downloader.py
w3cpull/geckodriver_darwin
w3cpull/geckodriver_linux
w3cpull/mime-types.txt
w3cpull/modifier.py
w3cpull/w3cpull.py
w3cpull.egg-info/PKG-INFO
w3cpull.egg-info/SOURCES.txt
w3cpull.egg-info/dependency_links.txt
w3cpull.egg-info/requires.txt
w3cpull.egg-info/top_level.txt