Metadata-Version: 2.1
Name: w3cpull
Version: 1.1.1
Summary: w3cpull is an application for pulling data from IBM w3 Connections.
Home-page: https://github.com/soulless-viewer/w3cpull
Author: Mikalai Lisitsa
Author-email: Mikalai.Lisitsa@ibm.com
License: MIT
Keywords: w3-connections w3c ibm
Platform: UNKNOWN
Requires-Python: >=3.6
